qark_behave/__init__.py
qark_behave/formatter.py
qark_behave-0.1.2.dist-info/LICENSE
qark_behave-0.1.2.dist-info/METADATA
qark_behave-0.1.2.dist-info/WHEEL
qark_behave-0.1.2.dist-info/top_level.txt
qark_behave-0.1.2.dist-info/RECORD
