Metadata-Version: 2.1
Name: qark-behave
Version: 0.1.2
Summary: QArk formatter for Behave
Author-email: Pablo Gibaja <gibajapablo.dev@gmail.com>
Project-URL: Homepage, https://github.com/PabloGibaja/qark-behave
Project-URL: Repository, https://github.com/PabloGibaja/qark-behave
Project-URL: Issues, https://github.com/PabloGibaja/qark-behave/issues
Classifier: Development Status :: 3 - Alpha
Classifier: Intended Audience :: Developers
Classifier: License :: OSI Approved :: MIT License
Classifier: Programming Language :: Python :: 3
Classifier: Programming Language :: Python :: 3.7
Classifier: Programming Language :: Python :: 3.8
Classifier: Programming Language :: Python :: 3.9
Classifier: Programming Language :: Python :: 3.10
Classifier: Programming Language :: Python :: 3.11
Classifier: Programming Language :: Python :: 3.12
Requires-Python: >=3.7
License-File: LICENSE
Requires-Dist: behave >=1.2.6
Requires-Dist: allure-behave >=2.9.0
Provides-Extra: dev
Requires-Dist: pytest >=6.0 ; extra == 'dev'
Requires-Dist: pytest-cov ; extra == 'dev'
Requires-Dist: black ; extra == 'dev'
Requires-Dist: flake8 ; extra == 'dev'
